net_emulator/__init__.py
net_emulator/double_flow.py
net_emulator/qoe_model.py
net_emulator/utils.py
net_emulator/common/__init__.py
net_emulator/common/sender_obs.py
net_emulator/config/__init__.py
net_emulator/config/constant.py
net_emulator/objects/__init__.py
net_emulator/objects/application.py
net_emulator/objects/block.py
net_emulator/objects/cc_base.py
net_emulator/objects/emulator.py
net_emulator/objects/engine.py
net_emulator/objects/link.py
net_emulator/objects/packet.py
net_emulator/objects/sender.py
net_emulator/player/__init__.py
net_emulator/player/aitrans_solution.py
net_emulator/player/block_selection.py
net_emulator/player/examples/__init__.py
net_emulator/player/examples/match_trace_rate.py
net_emulator/player/examples/reno.py
net_emulator-0.2.2.dist-info/METADATA
net_emulator-0.2.2.dist-info/WHEEL
net_emulator-0.2.2.dist-info/top_level.txt
net_emulator-0.2.2.dist-info/RECORD
