Metadata-Version: 2.1
Name: net-emulator
Version: 0.2.2
Summary: A package for net lab
Home-page: UNKNOWN
Author: Neptune17
Author-email: 1115876559@qq.com
License: UNKNOWN
Platform: UNKNOWN
Classifier: Programming Language :: Python :: 3
Classifier: License :: OSI Approved :: MIT License
Classifier: Operating System :: OS Independent
Requires-Python: >=3.6
